shadow/__init__.py
shadow/cli.py
shadow/log.py
shadow/renderer.py
shadow/search.py
shadow/shadow.py
shadowgen-0.3.2.dist-info/METADATA
shadowgen-0.3.2.dist-info/RECORD
shadowgen-0.3.2.dist-info/WHEEL
shadowgen-0.3.2.dist-info/entry_points.txt
shadowgen-0.3.2.dist-info/top_level.txt
