Metadata-Version: 2.1
Name: shadowgen
Version: 0.3.2
Summary: A comprehensive command line utility to render templates and ease code generation.
Home-page: https://github.com/karma0/shadow
Author: Bobby
Author-email: karma0@gmail.com
License: GNU General Public License v3
Keywords: shadow
Platform: UNKNOWN
Classifier: Development Status :: 3 - Alpha
Classifier: Environment :: Console
Classifier: Topic :: Utilities
Classifier: Intended Audience :: Developers
Classifier: Intended Audience :: Information Technology
Classifier: Intended Audience :: System Administrators
Classifier: License :: OSI Approved :: GNU General Public License v3 (GPLv3)
Classifier: Natural Language :: English
Classifier: Programming Language :: Python :: 3
Classifier: Programming Language :: Python :: 3.6
Classifier: Programming Language :: Python :: 3.7
Requires-Dist: Click (>=6.0)
Requires-Dist: Jinja2 (>=2.9.6)
